{
    "dialog_def": {
        "dialog": {
            "cancancel": false,
            "help1": " ",
            "help2": "$MENU_ACCEPT Continue",
            "platform": "gc",
            "text": "Press $ATTACK to perform a normal attack.  \\nPress $SMASH to perform a heavy attack.\\n\\nYou can chain attacks together to create melee combos.\\n\\nEXAMPLE:\\n$ATTACK + $ATTACK + $SMASH = Pop-up Attack"
        },
        "dialog": {
            "cancancel": false,
            "help1": " ",
            "help2": "$MENU_ACCEPT Continue",
            "platform": "ps2",
            "text": "Press $ATTACK to perform a normal attack.  \\nPress $SMASH to perform a heavy attack.\\n\\nYou can chain attacks together to create melee combos.\\n\\nEXAMPLE:\\n$ATTACK + $ATTACK + $SMASH = Pop-up Attack"
        },
        "dialog": {
            "cancancel": false,
            "help1": " ",
            "help2": "$MENU_ACCEPT Continue",
            "platform": "xbox",
            "text": "Press $ATTACK to perform a normal attack.  \\nPress $SMASH to perform a heavy attack.\\n\\nYou can chain attacks together to create melee combos.\\n\\nEXAMPLE:\\n$ATTACK, $ATTACK, $SMASH = Pop-up Attack"
        },
        "dialog": {
            "cancancel": false,
            "help1": " ",
            "help2": "$MENU_ACCEPT Continue",
            "text": "Press $ATTACK to perform a normal attack.  \\nPress $SMASH to perform a heavy attack.\\n\\nYou can chain attacks together to create melee combos.\\n\\nEXAMPLE:\\n$ATTACK + $ATTACK + $SMASH = Pop-up Attack"
        }
    }
}