<compile>
    <consoles>
        <console name="PC" uses__combined="False" />
        <console name="GameCube" uses__combined="True" />
        <console name="PS2" uses__combined="True" />
        <console name="PSP" uses__combined="True" />
        <console name="Xbox" uses__combined="True" />
    </consoles>
    <info folder="act3\infinite" name="infinite6" />
    <mods>
        <mod name="X2UP" />
    </mods>
    <pcUnmodified>
        <file path="actors\0001.igb" />
        <file path="actors\0100.igb" />
        <file path="actors\01_sin_cyclops.igb" />
        <file path="actors\0300.igb" />
        <file path="actors\03_sin_wolverine.igb" />
        <file path="actors\0400.igb" />
        <file path="actors\04_sin_storm.igb" />
        <file path="actors\0800.igb" />
        <file path="actors\08_sin_iceman.igb" />
        <file path="actors\4801.igb" />
        <file path="actors\48_mr_sinister.igb" />
        <file path="actors\7202.igb" />
        <file path="actors\7204.igb" />
        <file path="actors\7205.igb" />
        <file path="actors\72_infinite_captain.igb" />
        <file path="actors\7302.igb" />
        <file path="actors\7304.igb" />
        <file path="actors\7305.igb" />
        <file path="actors\73_infinite_soldier.igb" />
        <file path="actors\fightstyle_staff.igb" />
        <file path="automaps\act3\infinite\infinite6.zam" />
        <file path="conversations\act3\infinite\infinite6\3_infinite6_0020.engb" />
        <file path="conversations\act3\infinite\infinite6\3_infinite6_0025.engb" />
        <file path="conversations\act3\infinite\infinite6\3_infinite6_0030.engb" />
        <file path="data\entities\ents_sin_storm.xmlb" />
        <file path="data\entities\ents_storm.xmlb" />
        <file path="data\fightstyles\fightstyle_staff.xmlb" />
        <file path="hud\hud_head_3101.igb" />
        <file path="hud\hud_head_3201.igb" />
        <file path="hud\hud_head_4801.igb" />
        <file path="hud\hud_head_7201.igb" />
        <file path="hud\hud_head_7301.igb" />
        <file path="maps\act3\infinite\infinite6.boyb" />
        <file path="maps\act3\infinite\infinite6.chrb" />
        <file path="maps\act3\infinite\infinite6.engb" />
        <file path="maps\act3\infinite\infinite6.igb" />
        <file path="maps\act3\infinite\infinite6.navb" />
        <file path="models\bolton\claw_left.igb" />
        <file path="models\bolton\claw_right.igb" />
        <file path="models\chunks\brick_1.igb" />
        <file path="models\chunks\c_haarp_a.igb" />
        <file path="models\chunks\c_haarp_b.igb" />
        <file path="models\chunks\met_6.igb" />
        <file path="models\chunks\met_9.igb" />
        <file path="models\common\energy_regen_station.igb" />
        <file path="models\common\health_regen_station.igb" />
        <file path="models\infinite_plant\barrel_inf_th.igb" />
        <file path="models\infinite_plant\chair_inf_th.igb" />
        <file path="models\infinite_plant\clone_spawner_inf_a_b.igb" />
        <file path="models\infinite_plant\clone_spawner_stump_inf_a_b.igb" />
        <file path="models\infinite_plant\comp_console_01_inf_a.igb" />
        <file path="models\infinite_plant\comp_console_inf_a.igb" />
        <file path="models\infinite_plant\comp_console_inf_b.igb" />
        <file path="models\infinite_plant\comp_console_stump_inf_b.igb" />
        <file path="models\infinite_plant\crate_inf_th.igb" />
        <file path="models\infinite_plant\door_01_inf_a.igb" />
        <file path="models\infinite_plant\door_plexi_glass_inf_a.igb" />
        <file path="models\infinite_plant\glow_lightcone_inf_e.igb" />
        <file path="models\infinite_plant\lesser_machine_01_inf_a_b.igb" />
        <file path="models\infinite_plant\lesser_machine_01_stump_inf_b.igb" />
        <file path="models\infinite_plant\lesser_machine_02_inf_a_b.igb" />
        <file path="models\infinite_plant\lesser_machine_inf_a_b.igb" />
        <file path="models\infinite_plant\lesser_machine_stump_inf_a_b.igb" />
        <file path="models\infinite_plant\super_comp_cpu_inf_a_b.igb" />
        <file path="models\infinite_plant\super_comp_cpu_stump_inf_a_b.igb" />
        <file path="models\infinite_plant\super_comp_gpu_inf_a_b.igb" />
        <file path="models\infinite_plant\super_comp_gpu_stump_inf_a_b.igb" />
        <file path="models\infinite_plant\super_comp_monitor_inf_a_b.igb" />
        <file path="models\infinite_plant\super_comp_monitor_stump_inf_a_b.igb" />
        <file path="models\infinite_plant\super_comp_router_inf_a_b.igb" />
        <file path="models\infinite_plant\super_comp_router_stump_inf_a_b.igb" />
        <file path="models\infinite_plant\super_comp_storage_array_inf_a_b.igb" />
        <file path="models\infinite_plant\super_comp_storage_array_stump_inf_a_b.igb" />
        <file path="models\infinite_plant\super_comp_terminal_inf_a_b.igb" />
        <file path="models\infinite_plant\super_comp_terminal_stump_inf_a_b.igb" />
        <file path="models\infinite_plant\vert_pipe_inf_b.igb" />
        <file path="models\pickups\sketchpad.igb" />
        <file path="models\puzzles\null_hover_puz_a.igb" />
        <file path="models\puzzles\null_hover_stump_puz_a.igb" />
        <file path="models\tiles\infiniteplant\infiniteplant_d2a_w_a0.igb" />
        <file path="models\tiles\infiniteplant\infiniteplant_d2g_w_a0.igb" />
        <file path="models\tiles\infiniteplant\infiniteplant_d3a_w_a0.igb" />
        <file path="models\tiles\infiniteplant\infiniteplant_d3a_w_b0.igb" />
        <file path="models\tiles\infiniteplant\infiniteplant_d3a_w_c0.igb" />
        <file path="models\tiles\infiniteplant\infiniteplant_d3g_w_a0.igb" />
        <file path="models\tiles\infiniteplant\infiniteplant_d3g_w_b0.igb" />
        <file path="models\tiles\infiniteplant\infiniteplant_d3g_w_c0.igb" />
        <file path="models\tiles\infiniteplant\infiniteplant_daa_w_a0.igb" />
        <file path="models\tiles\infiniteplant\infiniteplant_dac_w_a0.igb" />
        <file path="models\tiles\infiniteplant\infiniteplant_dag_w_a0.igb" />
        <file path="models\tiles\infiniteplant\infiniteplant_dba_w_a0.igb" />
        <file path="models\tiles\infiniteplant\infiniteplant_dba_w_b0.igb" />
        <file path="models\tiles\infiniteplant\infiniteplant_dba_w_c0.igb" />
        <file path="models\tiles\infiniteplant\infiniteplant_dbc_w_a0.igb" />
        <file path="models\tiles\infiniteplant\infiniteplant_dbc_w_b0.igb" />
        <file path="models\tiles\infiniteplant\infiniteplant_dbc_w_c0.igb" />
        <file path="models\tiles\infiniteplant\infiniteplant_dbg_w_a0.igb" />
        <file path="models\tiles\infiniteplant\infiniteplant_dbg_w_b0.igb" />
        <file path="models\tiles\infiniteplant\infiniteplant_dbg_w_c0.igb" />
        <file path="models\tiles\infiniteplant\infiniteplant_dcc_w_a0.igb" />
        <file path="models\tiles\infiniteplant\infiniteplant_dfc_w_a0.igb" />
        <file path="models\tiles\infiniteplant\infiniteplant_dgc_w_a0.igb" />
        <file path="models\tiles\infiniteplant\infiniteplant_dhc_w_a0.igb" />
        <file path="scripts\act3\infinite\infinite6\all_done.py" />
        <file path="scripts\act3\infinite\infinite6\attack_em.py" />
        <file path="scripts\act3\infinite\infinite6\clone_death.py" />
        <file path="scripts\act3\infinite\infinite6\clone_spawn.py" />
        <file path="scripts\act3\infinite\infinite6\in_arena.py" />
        <file path="scripts\act3\infinite\infinite6\infinite6.py" />
        <file path="scripts\act3\infinite\infinite6\out_arena.py" />
        <file path="scripts\act3\infinite\infinite6\show_clone.py" />
        <file path="scripts\act3\infinite\infinite6\sin_cam.py" />
        <file path="scripts\act3\infinite\infinite6\sin_conv2.py" />
        <file path="scripts\act3\infinite\infinite6\sin_conv2_end.py" />
        <file path="scripts\act3\infinite\infinite6\sin_intro.py" />
        <file path="scripts\act3\infinite\infinite6\sin_spawn.py" />
        <file path="scripts\common\concept\art_pack7.py" />
        <file path="scripts\common\pylons\a3_null_deploy.py" />
        <file path="scripts\common\pylons\a3_null_retract.py" />
    </pcUnmodified>
    <filesIn__combined>
        <file path="hud\hud_head_3101.igb" />
        <file path="hud\hud_head_3201.igb" />
        <file path="hud\hud_head_4801.igb" />
        <file path="hud\hud_head_7201.igb" />
        <file path="hud\hud_head_7301.igb" />
        <file path="maps\act3\infinite\infinite6.igb" />
        <file path="models\bolton\claw_left.igb" />
        <file path="models\bolton\claw_right.igb" />
        <file path="models\chunks\brick_1.igb" />
        <file path="models\chunks\c_haarp_a.igb" />
        <file path="models\chunks\c_haarp_b.igb" />
        <file path="models\chunks\met_6.igb" />
        <file path="models\chunks\met_9.igb" />
        <file path="models\common\energy_regen_station.igb" />
        <file path="models\common\health_regen_station.igb" />
        <file path="models\infinite_plant\barrel_inf_th.igb" />
        <file path="models\infinite_plant\chair_inf_th.igb" />
        <file path="models\infinite_plant\clone_spawner_inf_a_b.igb" />
        <file path="models\infinite_plant\clone_spawner_stump_inf_a_b.igb" />
        <file path="models\infinite_plant\comp_console_01_inf_a.igb" />
        <file path="models\infinite_plant\comp_console_inf_a.igb" />
        <file path="models\infinite_plant\comp_console_inf_b.igb" />
        <file path="models\infinite_plant\comp_console_stump_inf_b.igb" />
        <file path="models\infinite_plant\crate_inf_th.igb" />
        <file path="models\infinite_plant\door_01_inf_a.igb" />
        <file path="models\infinite_plant\door_plexi_glass_inf_a.igb" />
        <file path="models\infinite_plant\glow_lightcone_inf_e.igb" />
        <file path="models\infinite_plant\lesser_machine_01_inf_a_b.igb" />
        <file path="models\infinite_plant\lesser_machine_01_stump_inf_b.igb" />
        <file path="models\infinite_plant\lesser_machine_02_inf_a_b.igb" />
        <file path="models\infinite_plant\lesser_machine_inf_a_b.igb" />
        <file path="models\infinite_plant\lesser_machine_stump_inf_a_b.igb" />
        <file path="models\infinite_plant\super_comp_cpu_inf_a_b.igb" />
        <file path="models\infinite_plant\super_comp_cpu_stump_inf_a_b.igb" />
        <file path="models\infinite_plant\super_comp_gpu_inf_a_b.igb" />
        <file path="models\infinite_plant\super_comp_gpu_stump_inf_a_b.igb" />
        <file path="models\infinite_plant\super_comp_monitor_inf_a_b.igb" />
        <file path="models\infinite_plant\super_comp_monitor_stump_inf_a_b.igb" />
        <file path="models\infinite_plant\super_comp_router_inf_a_b.igb" />
        <file path="models\infinite_plant\super_comp_router_stump_inf_a_b.igb" />
        <file path="models\infinite_plant\super_comp_storage_array_inf_a_b.igb" />
        <file path="models\infinite_plant\super_comp_storage_array_stump_inf_a_b.igb" />
        <file path="models\infinite_plant\super_comp_terminal_inf_a_b.igb" />
        <file path="models\infinite_plant\super_comp_terminal_stump_inf_a_b.igb" />
        <file path="models\infinite_plant\vert_pipe_inf_b.igb" />
        <file path="models\pickups\sketchpad.igb" />
        <file path="models\puzzles\null_hover_puz_a.igb" />
        <file path="models\puzzles\null_hover_stump_puz_a.igb" />
        <file path="models\tiles\infiniteplant\infiniteplant_d2a_w_a0.igb" />
        <file path="models\tiles\infiniteplant\infiniteplant_d2g_w_a0.igb" />
        <file path="models\tiles\infiniteplant\infiniteplant_d3a_w_a0.igb" />
        <file path="models\tiles\infiniteplant\infiniteplant_d3a_w_b0.igb" />
        <file path="models\tiles\infiniteplant\infiniteplant_d3a_w_c0.igb" />
        <file path="models\tiles\infiniteplant\infiniteplant_d3g_w_a0.igb" />
        <file path="models\tiles\infiniteplant\infiniteplant_d3g_w_b0.igb" />
        <file path="models\tiles\infiniteplant\infiniteplant_d3g_w_c0.igb" />
        <file path="models\tiles\infiniteplant\infiniteplant_daa_w_a0.igb" />
        <file path="models\tiles\infiniteplant\infiniteplant_dac_w_a0.igb" />
        <file path="models\tiles\infiniteplant\infiniteplant_dag_w_a0.igb" />
        <file path="models\tiles\infiniteplant\infiniteplant_dba_w_a0.igb" />
        <file path="models\tiles\infiniteplant\infiniteplant_dba_w_b0.igb" />
        <file path="models\tiles\infiniteplant\infiniteplant_dba_w_c0.igb" />
        <file path="models\tiles\infiniteplant\infiniteplant_dbc_w_a0.igb" />
        <file path="models\tiles\infiniteplant\infiniteplant_dbc_w_b0.igb" />
        <file path="models\tiles\infiniteplant\infiniteplant_dbc_w_c0.igb" />
        <file path="models\tiles\infiniteplant\infiniteplant_dbg_w_a0.igb" />
        <file path="models\tiles\infiniteplant\infiniteplant_dbg_w_b0.igb" />
        <file path="models\tiles\infiniteplant\infiniteplant_dbg_w_c0.igb" />
        <file path="models\tiles\infiniteplant\infiniteplant_dcc_w_a0.igb" />
        <file path="models\tiles\infiniteplant\infiniteplant_dfc_w_a0.igb" />
        <file path="models\tiles\infiniteplant\infiniteplant_dgc_w_a0.igb" />
        <file path="models\tiles\infiniteplant\infiniteplant_dhc_w_a0.igb" />
    </filesIn__combined>
</compile>