{
    "talents": {
        "talent": {
            "hidden": true,
            "name": "psy_resist",
            "level": {
                "count": 1,
                "powerup": {
                    "life": -1,
                    "affecter": {
                        "attribute": "resist_mental",
                        "level": 1
                    },
                    "affecter": {
                        "attribute": "slow_immune",
                        "level": 1
                    }
                }
            }
        },
        "talent": {
            "descname": "Psychic Slash",
            "description": "Psylocke slashes an enemy with her Psychic Blade, stunning them.",
            "descshort": "Melee",
            "icon": 0,
            "icon_texture": "textures/ui/psylocke_icons2.png",
            "name": "psy_p1",
            "power": "power1",
            "talentvalues": {
                "talentvalue": {
                    "level": 1,
                    "name": "psy_p1_req",
                    "value": 1
                },
                "talentvalue": {
                    "level": 20,
                    "name": "psy_p1_req",
                    "value": 58
                },
                "talentvalue": {
                    "level": 1,
                    "name": "psy_p1_dmg",
                    "value": "21 26"
                },
                "talentvalue": {
                    "level": 20,
                    "name": "psy_p1_dmg",
                    "value": "195 217"
                },
                "talentvalue": {
                    "level": 1,
                    "name": "psy_p1_pwr",
                    "value": 12
                },
                "talentvalue": {
                    "level": 20,
                    "name": "psy_p1_pwr",
                    "value": 126
                }
            },
            "level": {
                "count": 20,
                "description": "%psy_p1_dmg $DMG_MENTAL\\n%psy_p1_pwr $EP",
                "require": {
                    "cat": "level",
                    "level": "%psy_p1_req"
                }
            }
        },
        "talent": {
            "descname": "Cerebral Bolts",
            "description": "Psylocke throws bolts of Psychic Energy at enemies, immobilizing them. Levels up to increase the number of bolts.",
            "descshort": "Projectile",
            "icon": 1,
            "icon_texture": "textures/ui/psylocke_icons2.png",
            "name": "psy_p2",
            "power": "power2",
            "talentvalues": {
                "talentvalue": {
                    "level": 1,
                    "name": "psy_p2_req",
                    "value": 7
                },
                "talentvalue": {
                    "level": 18,
                    "name": "psy_p2_req",
                    "value": 58
                },
                "talentvalue": {
                    "level": 1,
                    "name": "psy_p2_dmg",
                    "value": "17 22"
                },
                "talentvalue": {
                    "level": 18,
                    "name": "psy_p2_dmg",
                    "value": "124 144"
                },
                "talentvalue": {
                    "level": 1,
                    "name": "psy_p2_num",
                    "value": 1
                },
                "talentvalue": {
                    "level": 18,
                    "name": "psy_p2_num",
                    "value": 7
                },
                "talentvalue": {
                    "level": 1,
                    "name": "psy_p2_pwr",
                    "value": 36
                },
                "talentvalue": {
                    "level": 18,
                    "name": "psy_p2_pwr",
                    "value": 135
                }
            },
            "level": {
                "count": 18,
                "description": "%psy_p2_dmg $DMG_MENTAL\\n%psy_p2_num bolt(s)\\n%psy_p2_pwr $EP",
                "require": {
                    "cat": "level",
                    "level": "%psy_p2_req"
                }
            }
        },
        "talent": {
            "descname": "Telekinetic Explosion",
            "description": "Psylocke unleashes an intense explosion of Telekinetic Energy that knocks back enemies and objects. Can build bridges.",
            "descshort": "Radial",
            "icon": 2,
            "icon_texture": "textures/ui/psylocke_icons2.png",
            "name": "psy_p3",
            "power": "power3",
            "talentvalues": {
                "talentvalue": {
                    "level": 1,
                    "name": "psy_p3_req",
                    "value": 14
                },
                "talentvalue": {
                    "level": 16,
                    "name": "psy_p3_req",
                    "value": 58
                },
                "talentvalue": {
                    "level": 1,
                    "name": "psy_p3_dmg",
                    "value": "30 36"
                },
                "talentvalue": {
                    "level": 16,
                    "name": "psy_p3_dmg",
                    "value": "82 93"
                },
                "talentvalue": {
                    "level": 1,
                    "name": "psy_p3_kb",
                    "value": 245
                },
                "talentvalue": {
                    "level": 16,
                    "name": "psy_p3_kb",
                    "value": 620
                },
                "talentvalue": {
                    "level": 1,
                    "name": "psy_p3_pwr",
                    "value": 46
                },
                "talentvalue": {
                    "level": 16,
                    "name": "psy_p3_pwr",
                    "value": 170
                }
            },
            "level": {
                "count": 16,
                "description": "%psy_p3_dmg Telekinetic Dmg\\n%psy_p3_kb $KB\\n%psy_p3_pwr $EP",
                "require": {
                    "cat": "level",
                    "level": "%psy_p3_req"
                }
            }
        },
        "talent": {
            "descname": "Kinetic Drill",
            "description": "Psylocke hurls herself forward with her Psychic Blade, doing $DMG_MENTAL and stunning nearby enemies then finishing with a powerful drop kick, doing $DMG_PHYSICAL and popup.",
            "descshort": "Charge",
            "icon": 13,
            "icon_texture": "textures/ui/psylocke_icons2.png",
            "name": "psy_p4",
            "power": "power4",
            "talentvalues": {
                "talentvalue": {
                    "level": 1,
                    "name": "psy_p4_req",
                    "value": 21
                },
                "talentvalue": {
                    "level": 11,
                    "name": "psy_p4_req",
                    "value": 58
                },
                "talentvalue": {
                    "level": 1,
                    "name": "psy_p4_dmg",
                    "value": "63 71"
                },
                "talentvalue": {
                    "level": 11,
                    "name": "psy_p4_dmg",
                    "value": "205 224"
                },
                "talentvalue": {
                    "level": 1,
                    "name": "psy_p4_pwr",
                    "value": 42
                },
                "talentvalue": {
                    "level": 11,
                    "name": "psy_p4_pwr",
                    "value": 116
                }
            },
            "level": {
                "count": 11,
                "description": "%psy_p4_dmg $DMG_MENTAL first hit\\n%psy_p4_dmg $DMG_PHYSICAL second hit\\n%psy_p4_pwr $EP",
                "require": {
                    "cat": "level",
                    "level": "%psy_p4_req"
                }
            }
        },
        "talent": {
            "descname": "Twirling Blade",
            "description": "Psylocke twirls about, slashing and tripping nearby enemies with a chance for a 'Deadly Strike' (33% instant $HP loss).",
            "descshort": "Melee",
            "icon": 11,
            "icon_texture": "textures/ui/psylocke_icons2.png",
            "name": "psy_p5",
            "power": "power5",
            "talentvalues": {
                "talentvalue": {
                    "level": 1,
                    "name": "psy_p5_req",
                    "value": 28
                },
                "talentvalue": {
                    "level": 11,
                    "name": "psy_p5_req",
                    "value": 58
                },
                "talentvalue": {
                    "level": 1,
                    "name": "psy_p5_dmg",
                    "value": "66 72"
                },
                "talentvalue": {
                    "level": 11,
                    "name": "psy_p5_dmg",
                    "value": "220 235"
                },
                "talentvalue": {
                    "level": 1,
                    "name": "%psy_p5_cne",
                    "value": 0.05
                },
                "talentvalue": {
                    "level": 11,
                    "name": "%psy_p5_cne",
                    "value": 0.19
                },
                "talentvalue": {
                    "level": 1,
                    "name": "psy_p5_pwr",
                    "value": 72
                },
                "talentvalue": {
                    "level": 11,
                    "name": "psy_p5_pwr",
                    "value": 152
                }
            },
            "level": {
                "count": 11,
                "description": "%psy_p5_dmg $DMG_MENTAL\\n%psy_p5_cne:p chance for Deadly Strike\\n%psy_p5_pwr $EP",
                "require": {
                    "cat": "level",
                    "level": "%psy_p5_req"
                },
                "powerup": {
                    "chance": "%psy_p5_cne",
                    "class": "atk_instant_pct",
                    "life": -1,
                    "no_stack": true,
                    "percent": 0.33,
                    "affecter": {
                        "attribute": "powerup_scope",
                        "scope_node": "psy_power5"
                    }
                },
                "require": {
                    "cat": "skill",
                    "item": "psy_p4",
                    "level": 1
                }
            }
        },
        "talent": {
            "descname": "Telepathic Hallucinations",
            "description": "Psylocke creates Psychic illusions that make nearby enemies flee in terror and leave them unable to use their powers for a time.",
            "descshort": "Debuff",
            "icon": 4,
            "icon_texture": "textures/ui/psylocke_icons2.png",
            "name": "psy_p6",
            "power": "power6",
            "type": "boost",
            "talentvalues": {
                "talentvalue": {
                    "level": 1,
                    "name": "psy_p6_req",
                    "value": 14
                },
                "talentvalue": {
                    "level": 11,
                    "name": "psy_p6_req",
                    "value": 58
                },
                "talentvalue": {
                    "level": 1,
                    "name": "psy_p6_lif",
                    "value": 2
                },
                "talentvalue": {
                    "level": 11,
                    "name": "psy_p6_lif",
                    "value": 12
                },
                "talentvalue": {
                    "level": 1,
                    "name": "psy_p6_pwr",
                    "value": 84
                },
                "talentvalue": {
                    "level": 11,
                    "name": "psy_p6_pwr",
                    "value": 458
                }
            },
            "level": {
                "count": 11,
                "description": "%psy_p6_lif seconds neutralized\\n%psy_p6_pwr $EP",
                "require": {
                    "cat": "level",
                    "level": "%psy_p6_req"
                },
                "require": {
                    "cat": "skill",
                    "item": "psy_p7",
                    "level": 1
                }
            }
        },
        "talent": {
            "descname": "Extrasensory Perception",
            "description": "Psylocke uses her Telepathy to enhance her allies' senses, increasing the entire team's Movement Speed for a time.",
            "descshort": "Boost",
            "icon": 3,
            "icon_texture": "textures/ui/psylocke_icons2.png",
            "name": "psy_p7",
            "power": "power7",
            "type": "boost",
            "talentvalues": {
                "talentvalue": {
                    "level": 1,
                    "name": "psy_p7_req",
                    "value": 7
                },
                "talentvalue": {
                    "level": 16,
                    "name": "psy_p7_req",
                    "value": 58
                },
                "talentvalue": {
                    "level": 1,
                    "name": "psy_p7_lif",
                    "value": 13
                },
                "talentvalue": {
                    "level": 16,
                    "name": "psy_p7_lif",
                    "value": 55
                },
                "talentvalue": {
                    "level": 1,
                    "name": "psy_p7_sd",
                    "value": 1.1
                },
                "talentvalue": {
                    "level": 16,
                    "name": "psy_p7_sd",
                    "value": 1.85
                },
                "talentvalue": {
                    "level": 1,
                    "name": "psy_p7_pwr",
                    "value": 64
                },
                "talentvalue": {
                    "level": 16,
                    "name": "psy_p7_pwr",
                    "value": 380
                }
            },
            "level": {
                "count": 16,
                "description": "%psy_p7_sd:s Movement Speed\\n%psy_p7_lif seconds\\n%psy_p7_pwr $EP",
                "require": {
                    "cat": "level",
                    "level": "%psy_p7_req"
                }
            }
        },
        "talent": {
            "descname": "Dual Wield",
            "description": "Psylocke wields two Psychic Blades at once, increasing her $AR for a time.",
            "descshort": "Boost",
            "icon": 5,
            "icon_texture": "textures/ui/psylocke_icons2.png",
            "name": "psy_p8",
            "power": "power8",
            "type": "boost",
            "talentvalues": {
                "talentvalue": {
                    "level": 1,
                    "name": "psy_p8_req",
                    "value": 21
                },
                "talentvalue": {
                    "level": 16,
                    "name": "psy_p8_req",
                    "value": 58
                },
                "talentvalue": {
                    "level": 1,
                    "name": "psy_p8_ar",
                    "value": 1.2
                },
                "talentvalue": {
                    "level": 16,
                    "name": "psy_p8_ar",
                    "value": 2.2
                },
                "talentvalue": {
                    "level": 1,
                    "name": "psy_p8_lif",
                    "value": 13
                },
                "talentvalue": {
                    "level": 16,
                    "name": "psy_p8_lif",
                    "value": 55
                },
                "talentvalue": {
                    "level": 1,
                    "name": "psy_p8_pwr",
                    "value": 132
                },
                "talentvalue": {
                    "level": 16,
                    "name": "psy_p8_pwr",
                    "value": 516
                }
            },
            "level": {
                "count": 16,
                "description": "%psy_p8_ar:s $AR\\n%psy_p8_lif seconds\\n%psy_p8_pwr $EP",
                "require": {
                    "cat": "level",
                    "level": "%psy_p8_req"
                },
                "require": {
                    "cat": "skill",
                    "item": "psy_ps1",
                    "level": 1
                }
            }
        },
        "talent": {
            "descname": "PSYCHIC ONSLAUGHT",
            "description": "Psylocke unleashes an onslaught of Psychic Energy that slows any enemies who survive it.",
            "descshort": "Blast",
            "icon": 6,
            "icon_texture": "textures/ui/psylocke_icons2.png",
            "name": "psy_p9",
            "power": "power9",
            "type": "xtreme",
            "talentvalues": {
                "talentvalue": {
                    "level": 1,
                    "name": "psy_p9_req",
                    "value": 15
                },
                "talentvalue": {
                    "level": 7,
                    "name": "psy_p9_req",
                    "value": 45
                },
                "talentvalue": {
                    "level": 1,
                    "name": "psy_p9_dmg",
                    "value": "85 96"
                },
                "talentvalue": {
                    "level": 7,
                    "name": "psy_p9_dmg",
                    "value": "279 309"
                },
                "talentvalue": {
                    "level": 1,
                    "name": "psy_p9_slw",
                    "value": 0.75
                },
                "talentvalue": {
                    "level": 7,
                    "name": "psy_p9_slw",
                    "value": 0.25
                },
                "talentvalue": {
                    "level": 1,
                    "name": "psy_p9_lif",
                    "value": 4
                },
                "talentvalue": {
                    "level": 7,
                    "name": "psy_p9_lif",
                    "value": 11
                }
            },
            "level": {
                "count": 7,
                "description": "%psy_p9_dmg $DMG_MENTAL\\n%psy_p9_slw:p slow for %psy_p9_lif seconds",
                "require": {
                    "cat": "level",
                    "level": "%psy_p9_req"
                },
                "require": {
                    "cat": "skill",
                    "item": "psy_p3",
                    "level": 1
                }
            }
        },
        "talent": {
            "descname": "CRIMSON DAWN",
            "description": "Using the power of Crimson Dawn, Psylocke makes herself and her allies invisible and increases everyone's $DR and $XP for a time.",
            "descshort": "Boost",
            "icon": 7,
            "icon_texture": "textures/ui/psylocke_icons2.png",
            "name": "psy_p10",
            "power": "power10",
            "type": "xtreme",
            "talentvalues": {
                "talentvalue": {
                    "level": 1,
                    "name": "psy_p10_req",
                    "value": 20
                },
                "talentvalue": {
                    "level": 5,
                    "name": "psy_p10_req",
                    "value": 40
                },
                "talentvalue": {
                    "level": 1,
                    "name": "psy_p10_dr",
                    "value": 1.2
                },
                "talentvalue": {
                    "level": 5,
                    "name": "psy_p10_dr",
                    "value": 2.6
                },
                "talentvalue": {
                    "level": 1,
                    "name": "psy_p10_xp",
                    "value": 1.5
                },
                "talentvalue": {
                    "level": 5,
                    "name": "psy_p10_xp",
                    "value": 1.5
                },
                "talentvalue": {
                    "level": 1,
                    "name": "psy_p10_lif",
                    "value": 15
                },
                "talentvalue": {
                    "level": 5,
                    "name": "psy_p10_lif",
                    "value": 45
                }
            },
            "level": {
                "count": 5,
                "description": "%psy_p10_dr:s $DR\\n%psy_p10_xp:s $XP\\n%psy_p10_lif seconds",
                "require": {
                    "cat": "level",
                    "level": "%psy_p10_req"
                },
                "require": {
                    "cat": "skill",
                    "item": "psy_p7",
                    "level": 1
                }
            }
        },
        "talent": {
            "descname": "Blade Mastery",
            "description": "Increases the size of Psylocke's Psychic Blade and increases damage and Critical chance of all powered and non-powered attacks.\\n(~41Also affects Dual Wield.~~)",
            "descshort": "Passive",
            "icon": 8,
            "icon_texture": "textures/ui/psylocke_icons2.png",
            "name": "psy_ps1",
            "talentvalues": {
                "talentvalue": {
                    "level": 1,
                    "name": "psy_ps1_req",
                    "value": 7
                },
                "talentvalue": {
                    "level": 15,
                    "name": "psy_ps1_req",
                    "value": 21
                },
                "talentvalue": {
                    "level": 1,
                    "name": "psy_ps1_dmg",
                    "value": 1.05
                },
                "talentvalue": {
                    "level": 15,
                    "name": "psy_ps1_dmg",
                    "value": 1.5
                },
                "talentvalue": {
                    "level": 1,
                    "name": "psy_ps1_crit",
                    "value": 0.01
                },
                "talentvalue": {
                    "level": 15,
                    "name": "psy_ps1_crit",
                    "value": 0.08
                },
                "talentvalue": {
                    "level": 1,
                    "name": "psy_ps1_ca",
                    "value": 1
                },
                "talentvalue": {
                    "level": 5,
                    "name": "psy_ps1_ca",
                    "value": 1
                },
                "talentvalue": {
                    "level": 6,
                    "name": "psy_ps1_ca",
                    "value": 0
                },
                "talentvalue": {
                    "level": 15,
                    "name": "psy_ps1_ca",
                    "value": 0
                },
                "talentvalue": {
                    "level": 1,
                    "name": "psy_ps1_cb",
                    "value": 0
                },
                "talentvalue": {
                    "level": 5,
                    "name": "psy_ps1_cb",
                    "value": 0
                },
                "talentvalue": {
                    "level": 6,
                    "name": "psy_ps1_cb",
                    "value": 1
                },
                "talentvalue": {
                    "level": 10,
                    "name": "psy_ps1_cb",
                    "value": 1
                },
                "talentvalue": {
                    "level": 11,
                    "name": "psy_ps1_cb",
                    "value": 0
                },
                "talentvalue": {
                    "level": 15,
                    "name": "psy_ps1_cb",
                    "value": 0
                },
                "talentvalue": {
                    "level": 1,
                    "name": "psy_ps1_cc",
                    "value": 0
                },
                "talentvalue": {
                    "level": 10,
                    "name": "psy_ps1_cc",
                    "value": 0
                },
                "talentvalue": {
                    "level": 11,
                    "name": "psy_ps1_cc",
                    "value": 1
                },
                "talentvalue": {
                    "level": 15,
                    "name": "psy_ps1_cc",
                    "value": 1
                }
            },
            "level": {
                "count": 5,
                "description": "%psy_ps1_dmg:s Dmg\\n+%psy_ps1_crit:p Critical chance\\nKunai-Sized Blade",
                "require": {
                    "cat": "level",
                    "level": "%psy_ps1_req"
                },
                "require": {
                    "cat": "skill",
                    "item": "mutantmaster",
                    "level": 1
                },
                "powerup": {
                    "life": -1,
                    "BoltOn": {
                        "bolt": "Bip01 R Hand",
                        "model": "models/bolton/psylocke_blade_01",
                        "slot": "ebolton_weapon"
                    },
                    "affecter": {
                        "affect_type": "scale",
                        "attribute": "damage",
                        "level": "%psy_ps1_dmg"
                    },
                    "affecter": {
                        "attribute": "atk_critical",
                        "level": "%psy_ps1_crit"
                    }
                }
            },
            "level": {
                "count": 5,
                "description": "%psy_ps1_dmg:s Dmg\\n+%psy_ps1_crit:p Critical chance\\nTanto-Sized Blade",
                "require": {
                    "cat": "level",
                    "level": "%psy_ps1_req"
                },
                "require": {
                    "cat": "skill",
                    "item": "mutantmaster",
                    "level": 1
                },
                "powerup": {
                    "life": -1,
                    "BoltOn": {
                        "bolt": "Bip01 R Hand",
                        "model": "models/bolton/psylocke_blade_02",
                        "slot": "ebolton_weapon"
                    },
                    "affecter": {
                        "affect_type": "scale",
                        "attribute": "damage",
                        "level": "%psy_ps1_dmg"
                    },
                    "affecter": {
                        "attribute": "atk_critical",
                        "level": "%psy_ps1_crit"
                    }
                }
            },
            "level": {
                "count": 5,
                "description": "%psy_ps1_dmg:s Dmg\\n+%psy_ps1_crit:p Critical chance\\nKatana-Sized Blade",
                "require": {
                    "cat": "level",
                    "level": "%psy_ps1_req"
                },
                "require": {
                    "cat": "skill",
                    "item": "mutantmaster",
                    "level": 1
                },
                "powerup": {
                    "life": -1,
                    "BoltOn": {
                        "bolt": "Bip01 R Hand",
                        "model": "models/bolton/psylocke_blade_03",
                        "slot": "ebolton_weapon"
                    },
                    "affecter": {
                        "affect_type": "scale",
                        "attribute": "damage",
                        "level": "%psy_ps1_dmg"
                    },
                    "affecter": {
                        "attribute": "atk_critical",
                        "level": "%psy_ps1_crit"
                    }
                }
            }
        },
        "talent": {
            "descname": "Psionic Combat",
            "description": "Adds $DMG_MENTAL to all non-powered Melee attacks.",
            "descshort": "Passive",
            "icon": 9,
            "icon_texture": "textures/ui/psylocke_icons2.png",
            "name": "psy_ps2",
            "talentvalues": {
                "talentvalue": {
                    "level": 1,
                    "name": "psy_ps2_req",
                    "value": 1
                },
                "talentvalue": {
                    "level": 15,
                    "name": "psy_ps2_req",
                    "value": 15
                },
                "talentvalue": {
                    "level": 1,
                    "name": "psy_ps2_dmg",
                    "value": 0.5
                },
                "talentvalue": {
                    "level": 15,
                    "name": "psy_ps2_dmg",
                    "value": 3.6
                }
            },
            "level": {
                "count": 15,
                "description": "+%psy_ps2_dmg:p $DMG_MENTAL",
                "require": {
                    "cat": "level",
                    "level": "%psy_ps2_req"
                },
                "powerup": {
                    "class": "add_attack",
                    "damagepercent": "%psy_ps2_dmg",
                    "damagetype": "dmg_mental",
                    "life": -1,
                    "special_fx": {
                        "effect": "char/psyloc/special_trail",
                        "how_used": "custom"
                    },
                    "affecter": {
                        "attribute": "powerup_scope",
                        "scope": {
                            "scope_attack": "punch"
                        },
                        "scope": {
                            "scope_attack": "kick"
                        },
                        "scope": {
                            "scope_non_powers": true
                        }
                    }
                }
            }
        },
        "talent": {
            "descname": "Precognition",
            "description": "Increases chance to dodge projectiles and all powered and non-powered Melee attacks. Also reflects a percentage of damage done by projectiles back at enemies.",
            "descshort": "Passive",
            "icon": 10,
            "icon_texture": "textures/ui/psylocke_icons2.png",
            "name": "psy_ps3",
            "talentvalues": {
                "talentvalue": {
                    "level": 1,
                    "name": "psy_ps3_req",
                    "value": 14
                },
                "talentvalue": {
                    "level": 15,
                    "name": "psy_ps3_req",
                    "value": 28
                },
                "talentvalue": {
                    "level": 1,
                    "name": "psy_ps3_cne",
                    "value": 0.05
                },
                "talentvalue": {
                    "level": 15,
                    "name": "psy_ps3_cne",
                    "value": 0.5
                },
                "talentvalue": {
                    "level": 1,
                    "name": "psy_ps3_ref",
                    "value": 0.05
                },
                "talentvalue": {
                    "level": 15,
                    "name": "psy_ps3_ref",
                    "value": 0.5
                }
            },
            "level": {
                "count": 15,
                "description": "%psy_ps3_cne:p chance to dodge\\n+%psy_ps3_ref:p Dmg done by projectiles reflected",
                "require": {
                    "cat": "level",
                    "level": "%psy_ps3_req"
                },
                "powerup": {
                    "life": -1,
                    "affecter": {
                        "attribute": "def_dodge",
                        "level": "%psy_ps3_cne",
                        "scope": {
                            "scope_attack": "punch"
                        },
                        "scope": {
                            "scope_attack": "kick"
                        },
                        "scope": {
                            "scope_attack": "projectile"
                        }
                    },
                    "affecter": {
                        "affect_type": "scale",
                        "attribute": "reflect_damage",
                        "level": "%psy_ps3_ref",
                        "scope": {
                            "scope_attack": "projectile"
                        }
                    }
                }
            }
        }
    }
}