<compile>
    <consoles>
        <console name="PC" />
        <console name="GameCube" />
        <console name="PS2" />
        <console name="PSP" />
        <console name="Xbox" />
    </consoles>
    <mods>
        <mod name="X2UP" />
    </mods>
    <info internalName="Svs_Ninja" skin="11801" psName="ps_svsninja" effectsFolder="svsnin" sounds="svsnin" />
    <pcUnmodified>
        <file path="actors\118_ninja.igb" />
        <file path="data\powerstyles\ps_svsninja.xmlb" />
        <file path="effects\char\svsnin\p1_power.xmlb" />
        <file path="data\powerstyles\svsnin\special_resurrect.xmlb" />
    </pcUnmodified>
</compile>