<compile>
    <consoles>
        <console name="PC" />
        <console name="GameCube" />
        <console name="PS2" />
        <console name="PSP" />
        <console name="Xbox" />
    </consoles>
    <mods>
        <mod name="X2UP" />
    </mods>
    <info internalName="Mercenary_Guard" skin="7701" psName="ps_mercenary" effectsFolder="merc" sounds="merc" />
    <variants>
        <variant type="b" skin="7704" />
    </variants>
    <pcUnmodified>
        <file path="actors\77_mercenary.igb" />
        <file path="data\entities\ents_merc.xmlb" />
        <file path="data\powerstyles\ps_mercenary.xmlb" />
        <file path="effects\char\merc\p2_impact.xmlb" />
        <file path="effects\char\merc\p2_power.xmlb" />
        <file path="effects\char\merc\p2_shot.xmlb" />
    </pcUnmodified>
    <maps>
        <map name="tutorial1" variant="b" status="noConvo" />
    </maps>
</compile>