<packagedef>
    <combat_is filename="on" />
    <bigconvmap filename="off" />
    <model filename="__combined.igb" />
    <model filename="maps/briefing/briefing4_30.igb" />
    <script filename="scripts/briefing/briefing4_30.py" />
    <script filename="scripts/briefing/briefing4_cancel.py" />
    <model filename="models/briefing_holo_models/4_20_apoctower_brain.igb" />
    <actoranimdb filename="actors/200_bishop.igb" />
    <actoranimdb filename="actors/200_iceman.igb" />
    <actoranimdb filename="actors/200_sunfire.igb" />
    <actoranimdb filename="actors/200_toad.igb" />
    <actoranimdb filename="actors/200_xavier.igb" />
    <actoranimdb filename="actors/zone_briefing4_30.igb" />
    <actorskin filename="actors/20001.igb" />
    <actorskin filename="actors/20010.igb" />
    <actorskin filename="actors/20014.igb" />
    <actorskin filename="actors/20023.igb" />
    <actorskin filename="actors/20024.igb" />
    <characters filename="maps/briefing/briefing4_30.chrb" />
    <zonexml filename="maps/briefing/briefing4_30.xmlb" />
    <zam filename="automaps/briefing/briefing4_30.zam" />
</packagedef>